tongban_report/__init__.py
tongban_report/main.py
tongban_report/utils/__init__.py
tongban_report/utils/base_util.py
tongban_report/utils/excel_util.py
tongban_report/utils/file_util.py
tongban_report/utils/func_report.py
tongban_report/utils/perf_util.py
tongban_report/utils/perf_util2.py
tongban_report/utils/safe_report.py
tongban_report/utils/upload_util.py
tongban_report-0.4.0.dist-info/licenses/LICENSE
tongban_report-0.4.0.dist-info/METADATA
tongban_report-0.4.0.dist-info/WHEEL
tongban_report-0.4.0.dist-info/entry_points.txt
tongban_report-0.4.0.dist-info/top_level.txt
tongban_report-0.4.0.dist-info/RECORD
