Metadata-Version: 2.4
Name: tongban_report
Version: 0.4.0
Summary: A short description of your package
Home-page: https://github.com/yourusername/your-package
Author: roger813
Author-email: roger813@163.com
License: MIT AND (Apache-2.0 OR BSD-2-Clause)
Classifier: Programming Language :: Python :: 3
Classifier: Operating System :: OS Independent
Requires-Python: >=3.6
License-File: LICENSE
Requires-Dist: python-docx
Requires-Dist: matplotlib
Requires-Dist: openpyxl
Dynamic: author
Dynamic: author-email
Dynamic: classifier
Dynamic: description
Dynamic: description-content-type
Dynamic: home-page
Dynamic: license
Dynamic: license-file
Dynamic: requires-dist
Dynamic: requires-python
Dynamic: summary
